{
  "missing_dates": [
    {
      "日付": "2025-11-22"
    },
    {
      "日付": "2025-11-23"
    },
    {
      "日付": "2025-11-24"
    },
    {
      "日付": "2025-11-25"
    },
    {
      "日付": "2025-11-26"
    },
    {
      "日付": "2025-11-27"
    },
    {
      "日付": "2025-11-28"
    },
    {
      "日付": "2025-11-29"
    },
    {
      "日付": "2025-11-30"
    },
    {
      "日付": "2025-12-01"
    },
    {
      "日付": "2025-12-02"
    }
  ],
  "check_types": [
    "レース詳細"
  ]
}